discogs_api/__init__.py
discogs_api/client.py
discogs_api/exceptions.py
discogs_api/fetchers.py
discogs_api/models.py
discogs_api/utils.py
discogs_api/tests/__init__.py
discogs_api/tests/make_symlinks.py
discogs_api/tests/test_core.py
discogs_api/tests/test_fetchers.py
discogs_api/tests/test_models.py
discogs_api/tests/test_utils.py
discogs_api-0.1.0.dist-info/LICENSE
discogs_api-0.1.0.dist-info/METADATA
discogs_api-0.1.0.dist-info/WHEEL
discogs_api-0.1.0.dist-info/top_level.txt
discogs_api-0.1.0.dist-info/RECORD
