Metadata-Version: 2.1
Name: discogs-api
Version: 0.1.0
Summary: Python interface to the Discogs REST API
Home-page: https://github.com/grawlinson/python-discogs-api
Author: George Rawlinson
Author-email: george@rawlinson.net.nz
License: UNKNOWN
Keywords: discogs api wrapper
Platform: UNKNOWN
Classifier: Development Status :: 4 - Beta
Classifier: Intended Audience :: Developers
Classifier: License :: OSI Approved :: BSD License
Classifier: Natural Language :: English
Classifier: Operating System :: OS Independent
Classifier: Programming Language :: Python :: 3
Classifier: Topic :: Internet
Classifier: Topic :: Software Development :: Libraries
Classifier: Topic :: Software Development :: Libraries :: Python Modules
Classifier: Topic :: Utilities
